<?xml version="1.0" encoding="UTF-8"?>
<TextureAtlas imagePath="erupt_05_1.png" width="512" height="512" scale_x="3.3299999" scale_y="3.3299999" blend="1" loop="1">
    <sprite n="抽" x="476" y="98" w="30" h="14" oX="246" oY="182" oW="348" oH="200" dr="60"/>
    <sprite n="抽_02" x="62" y="318" w="46" h="56" oX="236" oY="140" oW="348" oH="200" dr="60"/>
    <sprite n="抽_03" x="2" y="388" w="48" h="68" oX="239" oY="98" oW="348" oH="200" dr="60"/>
    <sprite n="抽_04" x="250" y="162" w="214" h="150" oX="79" oY="46" oW="348" oH="200" dr="60"/>
    <sprite n="抽_05" x="250" y="2" w="224" h="158" oX="73" oY="4" oW="348" oH="200" dr="60"/>
    <sprite n="抽_06" x="2" y="196" w="208" h="102" oX="69" oY="4" oW="348" oH="200" dr="60"/>
    <sprite n="抽_07" x="156" y="370" w="44" h="46" oX="68" oY="4" oW="348" oH="200" dr="60"/>
    <sprite n="抽_08" x="510" y="2" w="0" h="0" oW="348" oH="200" dr="60"/>
    <sprite n="抽_09" x="476" y="2" w="32" h="38" oX="221" oY="164" oW="348" oH="200" r="y" dr="60"/>
    <sprite n="抽_10" x="466" y="162" w="44" h="50" oX="215" oY="112" oW="348" oH="200" dr="60"/>
    <sprite n="抽_11" x="110" y="318" w="46" h="50" oX="211" oY="56" oW="348" oH="200" dr="60"/>
    <sprite n="抽_12" x="118" y="422" w="44" h="46" oX="210" oY="4" oW="348" oH="200" dr="60"/>
    <sprite n="抽_13" x="476" y="82" w="30" h="14" oX="72" oY="182" oW="348" oH="200" dr="60"/>
    <sprite n="抽_14" x="70" y="452" w="46" h="56" oX="63" oY="140" oW="348" oH="200" dr="60"/>
    <sprite n="抽_15" x="2" y="458" w="66" h="50" oX="64" oY="98" oW="348" oH="200" r="y" dr="60"/>
    <sprite n="抽_16" x="2" y="318" w="58" h="68" oX="62" oY="47" oW="348" oH="200" dr="60"/>
    <sprite n="抽_17" x="52" y="388" w="60" h="62" oX="61" oY="4" oW="348" oH="200" r="y" dr="60"/>
    <sprite n="抽_18" x="2" y="2" w="246" h="192" oX="82" oY="4" oW="348" oH="200" dr="60"/>
    <sprite n="抽_19" x="114" y="370" w="40" h="50" oX="293" oY="138" oW="348" oH="200" dr="60"/>
    <sprite n="抽_20" x="466" y="266" w="44" h="50" oX="288" oY="84" oW="348" oH="200" dr="60"/>
    <sprite n="抽_21" x="466" y="214" w="44" h="50" oX="285" oY="28" oW="348" oH="200" dr="60"/>
    <sprite n="抽_22" x="476" y="114" w="18" h="36" oX="287" oY="3" oW="348" oH="200" r="y" dr="60"/>
    <sprite n="抽_23" x="510" y="2" w="0" h="0" oW="348" oH="200" dr="60"/>
    <sprite n="抽_24" x="476" y="42" w="32" h="38" oX="59" oY="164" oW="348" oH="200" r="y" dr="60"/>
    <sprite n="抽_25" x="202" y="300" w="46" h="42" oX="54" oY="113" oW="348" oH="200" r="y" dr="60"/>
    <sprite n="抽_26" x="164" y="418" w="44" h="44" oX="49" oY="57" oW="348" oH="200" dr="60"/>
</TextureAtlas>
